__init__.py
MyGICA/A_compiler.py
MyGICA/srt2MyGICA.py
MyGICA/structure.py
MyGICA/time_based_cache_cleaner.py
MyGICA/betterer/__init__.py
mygica-1.0a0.dist-info/licenses/LICENSE
mygica-1.0a0.dist-info/METADATA
mygica-1.0a0.dist-info/WHEEL
mygica-1.0a0.dist-info/entry_points.txt
mygica-1.0a0.dist-info/top_level.txt
mygica-1.0a0.dist-info/RECORD
