Metadata-Version: 2.4
Name: MyGICA
Version: 1.0a0
Summary: 剪辑 MyGICA 视频的 MyGICA 工具, MyGICA 即 MyGO!!!!! & MUJICA
Author-email: betterer <2534666876@qq.com>
Classifier: Programming Language :: Python :: 3
Classifier: License :: OSI Approved :: GNU Affero General Public License v3
Classifier: Operating System :: OS Independent
Classifier: Development Status :: 3 - Alpha
Classifier: Topic :: Scientific/Engineering
Classifier: Topic :: Multimedia :: Video
Classifier: Topic :: Multimedia :: Sound/Audio
Classifier: Environment :: Console
Requires-Python: >=3.11
License-File: LICENSE
Requires-Dist: click>=8.3.1
Requires-Dist: dacite>=1.9.2
Requires-Dist: loguru>=0.7.3
Requires-Dist: natsort>=8.4.0
Requires-Dist: numpy>=2.3.3
Requires-Dist: pillow>=11.3.0
Requires-Dist: pysrt>=1.1.2
Dynamic: license-file
